Workbook

Sheet Summary
A1: My Office Bot - Launch Budget
A2: Prepared by Claude, reviewed with ChatGPT (R&D 009), 2026-10-23. Excludes your time, marketing and AI tool subscriptions. Change numbers on the Inputs tab.
B4: Lean ($) | C4: Recommended ($) | D4: What it means
A5: Already spent | B5: ='One-Time'!B18 | C5: ='One-Time'!C18 | D5: The domain.
A6: One-time setup (incl. already spent) | B6: ='One-Time'!B17 | C6: ='One-Time'!C17 | D6: LLC, texting registration, legal, insurance - see One-Time tab.
A7: Monthly while building | B7: =Monthly!B16 | C7: =Monthly!B16 | D7: Free tiers until the beta engine works.
A8: Monthly during private beta | B8: =Monthly!C16 | C8: =Monthly!D16 | D8: Hosting, database, texting, usage for the beta contractors.
A9: First 3 months total | B9: =B6+B7*Inputs!$B$11+B8*Inputs!$B$12 | C9: =C6+C7*Inputs!$B$11+C8*Inputs!$B$12 | D9: One-time + build month(s) + beta months.
A10: Suggested cash reserve (recommended + contingency, rounded up) | C10: =ROUNDUP(C9*(1+Inputs!$B$19),-2) | D10: The number to set aside to launch.
A12: Break-even
A13: Left over per paying customer after texts and card fees | C13: =Inputs!$B$14-Inputs!$B$6*Inputs!$B$25-(Inputs!$B$14*(Inputs!$B$16+Inputs!$B$18)+Inputs!$B$17) | D13: $49 minus messaging and Stripe for one location.
A14: Fixed monthly costs (recommended beta, excluding usage) | C14: =Monthly!D16-Monthly!D9 | D14: Hosting, database, texting fees, mailbox.
A15: Paying customers needed to cover fixed monthly costs | C15: =IFERROR(ROUNDUP(C14/C13,0),0) | D15: Excludes legal, insurance, support time and marketing.
A17: Important
A18: • Lean is a technical minimum, not a legally reviewed, insured beta. Recommended is the realistic launch number.
A19: • Do the lawyer review and get insurance before outside contractors receive automated texts and calls.
A20: • Start the LLC + EIN + Twilio registration first: texting approval takes 1-3 weeks. Email alerts work meanwhile.
A21: • All vendor prices are list prices checked 2026-10-23, not quotes.

Sheet Inputs
A1: Inputs & Assumptions
A2: Blue = numbers you can change. Yellow = key assumptions. Every other tab recalculates from these. Vendor prices checked 2026-10-23; re-check at signup.
A4: Assumption | B4: Value | C4: Unit | D4: Source / note
A5: Contractors in the private beta | B5: 10 | C5: contractors | D5: Planning number for the beta (3-10).
A6: Leads per contractor per month | B6: 40 | C6: leads | D6: Typical small contractor website; replace with real data after 10 contractors.
A7: Messaging cost per lead - lean | B7: 0.07 | C7: $ / lead | D7: ~4 SMS segments + 1 ack reply + 25% get a 1-min call + 3 emails (COSTS.md §5).
A8: Messaging cost per lead - expected | B8: 0.12 | C8: $ / lead | D8: More segments, retries, longer calls. Agreed with ChatGPT (R&D 007).
A9: Messaging cost per lead - stress | B9: 0.28 | C9: $ / lead | D9: Heavy escalation, more contacts, retries.
A10: Scenario used (1 = lean, 2 = expected, 3 = stress) | B10: 2 | C10: 1 / 2 / 3 | D10: Change to 1 or 3 to see best / worst case.
A11: Build months (free tiers, no customers) | B11: 1 | C11: months | D11: Vercel Hobby + Supabase Free + Resend Free while building.
A12: Beta months in the first 3 months | B12: 2 | C12: months
A13: Paying customers at paid launch | B13: 25 | C13: customers | D13: Used on the Monthly tab's 'Paid launch' column.
A14: Price per location per month | B14: 49 | C14: $ / month | D14: Decision D17.
A15: Agency wholesale price per location | B15: 29 | C15: $ / month | D15: Decision D17.
A16: Stripe card fee | B16: 0.029 | C16: % of charge | D16: https://stripe.com/pricing
A17: Stripe fixed fee per charge | B17: 0.3 | C17: $ / charge | D17: https://stripe.com/pricing
A18: Stripe Billing fee | B18: 0.007 | C18: % of charge | D18: Stripe Billing (subscriptions).
A19: Contingency on recommended budget | B19: 0.1 | C19: % | D19: ChatGPT recommends 10-15%.
A20: Texas LLC filing fee (Form 205) | B20: 300 | C20: $ | D20: Texas SOS; https://www.sos.state.tx.us
A21: Texas SOS online card surcharge | B21: 0.0225 | C21: % | D21: 2.25% + $0.25 per SOSDirect card payment (ChatGPT R&D 009).
A22: Texas SOS card surcharge fixed part | B22: 0.25 | C22: $
A23: Twilio local number | B23: 1.15 | C23: $ / month | D23: https://www.twilio.com/en-us/sms/pricing/us
A24: Twilio numbers needed | B24: 2 | C24: numbers | D24: One alert sender + one support line.
A25: Messaging cost per lead - selected scenario | B25: =CHOOSE($B$10,B7,B8,B9) | C25: $ / lead | D25: Picks lean / expected / stress from the scenario number above.

Sheet One-Time
A1: One-Time Setup Costs
A2: Pay once to get started. Lean = minimum to run a real beta. Recommended = what Claude and ChatGPT advise before outside contractors use it.
A4: Item | B4: Lean ($) | C4: Recommended ($) | D4: Status | E4: When | F4: Notes / source
A5: Domain myofficebot.app (year 1) | B5: 8.2 | C5: 8.2 | D5: PAID | E5: Done | F5: Cloudflare Registrar. Renews at $14.20/yr in Oct 2027.
A6: Texas LLC filing + online card fee | B6: =Inputs!$B$20*(1+Inputs!$B$21)+Inputs!$B$22 | C6: =Inputs!$B$20*(1+Inputs!$B$21)+Inputs!$B$22 | D6: To do | E6: Before Twilio registration | F6: Needed for the EIN and the texting registration.
A7: EIN (IRS tax ID) | B7: 0 | C7: 0 | D7: To do | E7: Right after the LLC | F7: Free at irs.gov.
A8: Twilio texting brand registration | B8: 4.5 | C8: 46 | D8: To do | E8: Week 1 (takes 1-3 weeks) | F8: Lean = Low-Volume Standard brand (lower throughput, fine for a pilot if Twilio approves). Recommended = Standard brand with vetting.
A9: Twilio campaign vetting | B9: 15 | C9: 15 | D9: To do | E9: With brand registration | F9: https://www.twilio.com/en-us/phone-numbers/a2p-10dlc
A10: Twilio prepaid balance | B10: 20 | C10: 20 | D10: To do | E10: At Twilio signup | F10: Cash needed up front; it is then used up by texts/calls (not an extra cost).
A11: Terms & privacy from a template service | B11: 100 | C11: 0 | D11: To do | E11: Before beta | F11: Fine for internal testing only; replaced by the lawyer review in Recommended.
A12: Lawyer review: terms, privacy, SMS/call consent | B12: 0 | C12: 2000 | D12: To do | E12: Before outside contractors | F12: Planning figure; typical range $1,500-3,000.
A13: USPTO trademark (1 class) | B13: 0 | C13: 350 | D13: Optional | E13: Before spending on branding | F13: Base fee $350 per class; counsel decides class 9 and/or 42.
A14: getmyofficebot.com (catch .com typers) | B14: 0 | C14: 11.17 | D14: Optional | E14: Any time | F14: Cloudflare .com price from Nov 1, 2026.
A15: Cyber / tech E&O insurance (year 1) | B15: 0 | C15: 1500 | D15: To do | E15: Before outside contractors | F15: Planning figure ($1,000-2,000); get a real quote.
A16: Registered agent | B16: 0 | C16: 0 | D16: Decide | E16: With the LLC | F16: $0 if you act as your own agent; ~$50-150/yr for a service.
A17: Total one-time | B17: =SUM(B5:B16) | C17: =SUM(C5:C16)
A18: Already spent | B18: =SUMIFS(B5:B16,D5:D16,"PAID") | C18: =SUMIFS(C5:C16,D5:D16,"PAID")

Sheet Monthly
A1: Monthly Running Costs
A2: Per month, by phase. Messaging and Stripe lines are formulas driven by the Inputs tab.
A4: Service | B4: Build ($/mo) | C4: Beta - lean ($/mo) | D4: Beta - recommended ($/mo) | E4: Paid launch ($/mo) | F4: Notes / source
A5: Vercel hosting | B5: 0 | C5: 20 | D5: 20 | E5: 20 | F5: Hobby is free but non-commercial; Pro $20/seat for the real beta. https://vercel.com/pricing
A6: Supabase database + login | B6: 0 | C6: 25 | D6: 25 | E6: 25 | F6: Free tier pauses idle projects, no backups; Pro $25. https://supabase.com/pricing
A7: Twilio texting campaign fee | B7: 0 | C7: 1.5 | D7: 10 | E7: 10 | F7: Lean = low-volume campaign (~$1.50); Recommended = standard (~$10).
A8: Twilio phone numbers | B8: 0 | C8: =Inputs!$B$23*Inputs!$B$24 | D8: =Inputs!$B$23*Inputs!$B$24 | E8: =Inputs!$B$23*Inputs!$B$24 | F8: From Inputs: price x count.
A9: Texts & calls usage | B9: 0 | C9: =Inputs!$B$5*Inputs!$B$6*Inputs!$B$25 | D9: =Inputs!$B$5*Inputs!$B$6*Inputs!$B$25 | E9: =Inputs!$B$13*Inputs!$B$6*Inputs!$B$25 | F9: Contractors (or customers) x leads x cost per lead, from Inputs.
A10: Resend email | B10: 0 | C10: 0 | D10: 0 | E10: 20 | F10: Free up to 3,000 emails/mo; Pro $20 for 50k. https://resend.com/pricing
A11: Business mailbox (Google Workspace) | B11: 0 | C11: 0 | D11: 7 | E11: 7 | F11: Lean = free Cloudflare Email Routing (forward only). $7/user annual plan.
A12: Monitoring (Better Stack, Sentry) | B12: 0 | C12: 0 | D12: 0 | E12: 0 | F12: Free tiers to start.
A13: Bookkeeping software | B13: 0 | C13: 0 | D13: 0 | E13: 35 | F13: Optional; free options exist.
A14: Stripe fees | B14: 0 | C14: 0 | D14: 0 | E14: =Inputs!$B$13*(Inputs!$B$14*(Inputs!$B$16+Inputs!$B$18)+Inputs!$B$17) | F14: Paying customers x (price x (card % + Billing %) + $0.30).
A15: Domain renewal | B15: 0 | C15: 0 | D15: 0 | E15: 0 | F15: Year 1 prepaid; renews $14.20/yr from Oct 2027.
A16: Total per month | B16: =SUM(B5:B15) | C16: =SUM(C5:C15) | D16: =SUM(D5:D15) | E16: =SUM(E5:E15)
A18: Paid launch: revenue per month | E18: =Inputs!$B$13*Inputs!$B$14
A19: Paid launch: left over after costs | E19: =E18-E16
